Metadata-Version: 1.0
Name: setuptools-hg
Version: 0.4
Summary: Setuptools/distribute plugin for finding files under Mercurial version control.
Home-page: http://bitbucket.org/jezdez/setuptools_hg/
Author: Jannis Leidel
Author-email: jannis@leidel.info
License: GPL2
Platform: UNKNOWN
Classifier: Development Status :: 5 - Production/Stable
Classifier: Programming Language :: Python
Classifier: Programming Language :: Python :: 2
Classifier: Programming Language :: Python :: 2.4
Classifier: Programming Language :: Python :: 2.5
Classifier: Programming Language :: Python :: 2.6
Classifier: Programming Language :: Python :: 2.7
Classifier: Programming Language :: Python :: 3
Classifier: Programming Language :: Python :: 3.1
Classifier: Programming Language :: Python :: 3.2
Classifier: Intended Audience :: Developers
Classifier: Operating System :: OS Independent
Classifier: License :: OSI Approved :: GNU General Public License (GPL)
Classifier: Topic :: Software Development :: Version Control
Classifier: Framework :: Setuptools Plugin
